helper/__init__.py
helper/spark_helper.py
k8s_spark_helper/__init__.py
k8s_spark_helper/spark_helper.py
k8s_spark_helper_liangdao_data-0.0.3.dist-info/LICENSE
k8s_spark_helper_liangdao_data-0.0.3.dist-info/METADATA
k8s_spark_helper_liangdao_data-0.0.3.dist-info/WHEEL
k8s_spark_helper_liangdao_data-0.0.3.dist-info/top_level.txt
k8s_spark_helper_liangdao_data-0.0.3.dist-info/RECORD
