Metadata-Version: 2.1
Name: k8s-spark-helper-liangdao-data
Version: 0.0.3
Summary: Run spark task in k8s
Home-page: 
Author: yuchao.li
Author-email: yuchao.li@liangdao.ai
Classifier: Programming Language :: Python :: 3
Classifier: License :: OSI Approved :: MIT License
Classifier: Operating System :: OS Independent
License-File: LICENSE
